<xml xmlns="http://www.w3.org/1999/xhtml" collection="true">
  <block type="controls_if" id="vM4*snr!2_a#pu!Hhc)P" collapsed="true">
    <value name="IF0">
      <block type="logic_boolean" id="@}cMb-MJsYpYRWo!=1]|">
        <field name="BOOL">TRUE</field>
      </block>
    </value>
    <statement name="DO0">
      <block type="notify" id="F$y[4(*,Zj[Iwamo8)j," collapsed="true">
        <field name="NOTIFICATION_TYPE">info</field>
        <field name="NOTIFICATION_SOUND">silent</field>
        <value name="MESSAGE">
          <shadow type="text" id="6m|yaBB_RK_OCCxN#4^X">
            <field name="TEXT">Bot "Bola Giratória Molhada" By: Mauricio Joseph Coin</field>
          </shadow>
        </value>
        <next>
          <block type="variables_set" id="1|0ya=+(W,Gv`^rlj+rT">
            <field name="VAR" id="~%.=rbNr?KM7ubba*tgT" variabletype="">Vezes para fechar venda</field>
            <value name="VALUE">
              <block type="math_number" id="Fzu=_(:Ym//c{4bJfxkC">
                <field name="NUM">0</field>
              </block>
            </value>
            <next>
              <block type="variables_set" id="to#Xq{3nN`6YZfQ3Iqhb">
                <field name="VAR" id="d`]utxP|JY+Ff~tP4,il" variabletype="">Muda</field>
                <value name="VALUE">
                  <block type="text" id="lFtv]eyfG$@/6@|IWHs^">
                    <field name="TEXT">SIM</field>
                  </block>
                </value>
                <next>
                  <block type="variables_set" id="qSNwYDy8_sHyDu;JJ]v)">
                    <field name="VAR" id="!S9tAx*uwZHfLiV/iOWn" variabletype="">Max Loss Amount</field>
                    <value name="VALUE">
                      <block type="math_number" id="5),Co^^gBX`umJS2$AS5">
                        <field name="NUM">30000</field>
                      </block>
                    </value>
                    <next>
                      <block type="variables_set" id="X)]C^zXC,0LdD=8(iX/^">
                        <field name="VAR" id="pya!K;R~l.?5sSArRGL|" variabletype="">Expected Profit</field>
                        <value name="VALUE">
                          <block type="math_number" id="iwOaGU%bvdTaPyh9HaGn">
                            <field name="NUM">200000</field>
                          </block>
                        </value>
                        <next>
                          <block type="variables_set" id="tT.G_**78WVllqm~ej?R">
                            <field name="VAR" id="q`wD~D{:QdBYI{bq@j0l" variabletype="">Saldo Inicial</field>
                            <value name="VALUE">
                              <block type="math_number" id="_.nCure^$}0X#Xs@Syu*">
                                <field name="NUM">162</field>
                              </block>
                            </value>
                            <next>
                              <block type="variables_set" id="OKv!f~6Ebxx2L*Ugrk@5">
                                <field name="VAR" id="gH,d5]cT7K}$T19nB{D)" variabletype="">Valor MG</field>
                                <value name="VALUE">
                                  <block type="text_prompt_ext" id="@..Uq81M^0d}7s~oIunz">
                                    <mutation type="NUMBER"></mutation>
                                    <field name="TYPE">NUMBER</field>
                                    <value name="TEXT">
                                      <shadow type="text" id="_h%dh{kIREf;Q5|Fn2g)">
                                        <field name="TEXT">Valor do MG</field>
                                      </shadow>
                                    </value>
                                  </block>
                                </value>
                                <next>
                                  <block type="variables_set" id="C?*Y.3i|m^Kh!L/gVc;2">
                                    <field name="VAR" id="m`I0?1zU6E5)^OBk7V7J" variabletype="">Quantos MG ?</field>
                                    <value name="VALUE">
                                      <block type="text_prompt_ext" id="PgXRmzX%/xlanCWGglJ}">
                                        <mutation type="NUMBER"></mutation>
                                        <field name="TYPE">NUMBER</field>
                                        <value name="TEXT">
                                          <shadow type="text" id="`fiZ!3E/4ZmxnxU}$F`.">
                                            <field name="TEXT">Quantos MG</field>
                                          </shadow>
                                        </value>
                                      </block>
                                    </value>
                                    <next>
                                      <block type="variables_set" id="Kf?=*TF]ZVND|eXXvr,Q" collapsed="true">
                                        <field name="VAR" id="Z3ltA`h{mVZkzZLX6lKS" variabletype="">Chave do Reset do Martingale</field>
                                        <value name="VALUE">
                                          <block type="logic_boolean" id="r..y+WI9C)u:*C_?Kd@!">
                                            <field name="BOOL">FALSE</field>
                                          </block>
                                        </value>
                                        <next>
                                          <block type="variables_set" id="{CdFV(y4f9T?vEvN2-Um" collapsed="true">
                                            <field name="VAR" id="!t0[3x}A0T^neFcYzn:x" variabletype="">Contador de Martingale</field>
                                            <value name="VALUE">
                                              <block type="math_number" id="5{ky^0BXLFd8KF?D=`*h">
                                                <field name="NUM">0</field>
                                              </block>
                                            </value>
                                            <next>
                                              <block type="variables_set" id="j3i`kGgIs~omqH:]sb%R">
                                                <field name="VAR" id="ZUBkr,Y,|Pw=A+o_A{pG" variabletype="">---------------------------BB_1--------------------</field>
                                                <value name="VALUE">
                                                  <block type="math_number" id="p`8Sfa[/nS8G^h@h]3UV">
                                                    <field name="NUM">1</field>
                                                  </block>
                                                </value>
                                                <next>
                                                  <block type="variables_set" id="H!BPHF0yn9!RW8?BLTVn">
                                                    <field name="VAR" id=".XI*$qx}tqKhrKY03}T!" variabletype="">BB_Periodo</field>
                                                    <value name="VALUE">
                                                      <block type="math_number" id="GTXhp4Ub746+r(j2|eXJ">
                                                        <field name="NUM">20</field>
                                                      </block>
                                                    </value>
                                                    <next>
                                                      <block type="variables_set" id=";{bCyRu-?bWTQ?a]?)Jm">
                                                        <field name="VAR" id="Od!wB?Zr^=_fd9[_fjhj" variabletype="">BB_Desvio_UP</field>
                                                        <value name="VALUE">
                                                          <block type="math_number" id="*$68W9a/StL65-`F]+j0">
                                                            <field name="NUM">1.5</field>
                                                          </block>
                                                        </value>
                                                        <next>
                                                          <block type="variables_set" id="~7Q[aA,1Z`T*j%C1OR=;">
                                                            <field name="VAR" id="1w$Cb-)v8-Oy{haZ5_CA" variabletype="">BB_Desvio_Down</field>
                                                            <value name="VALUE">
                                                              <block type="math_number" id="o5dT:z|O^`usZ}ND;7)S">
                                                                <field name="NUM">1.5</field>
                                                              </block>
                                                            </value>
                                                            <next>
                                                              <block type="variables_set" id="b/%[H6z*U-g[g78xQKu/">
                                                                <field name="VAR" id="akJm$,H?deIKdVBXqX7X" variabletype="">Media movel maior</field>
                                                                <value name="VALUE">
                                                                  <block type="math_number" id="r0`Nz,5s;UlfDeYrbyHu">
                                                                    <field name="NUM">20</field>
                                                                  </block>
                                                                </value>
                                                                <next>
                                                                  <block type="variables_set" id="GxGoedq#Y9GG{GuE*}5T">
                                                                    <field name="VAR" id="h}RrA:@da80kW@fsw1j!" variabletype="">Media movel menor</field>
                                                                    <value name="VALUE">
                                                                      <block type="math_number" id="Ih@j1aN;-ph9T_k2ZkG0">
                                                                        <field name="NUM">10</field>
                                                                      </block>
                                                                    </value>
                                                                    <next>
                                                                      <block type="variables_set" id="sW:b~doHuK=/z$9y$|6@">
                                                                        <field name="VAR" id="6#)y*tu(Wg4+XPq/Wku$" variabletype="">----------------------------------bb_2-------QUE AGORA É 1°--------</field>
                                                                        <value name="VALUE">
                                                                          <block type="math_number" id="+TgXz%^]tTO:C8Tll%Vh">
                                                                            <field name="NUM">2</field>
                                                                          </block>
                                                                        </value>
                                                                        <next>
                                                                          <block type="variables_set" id="@^kU}YH)Ll@-9@ap+F0a">
                                                                            <field name="VAR" id="RS1i-#Ksp]Ny$-8/g0+8" variabletype="">BB2_P</field>
                                                                            <value name="VALUE">
                                                                              <block type="math_number" id=",92@)i5pX9.Y:j$A6?cn">
                                                                                <field name="NUM">15</field>
                                                                              </block>
                                                                            </value>
                                                                            <next>
                                                                              <block type="variables_set" id="FL*8;mf%8m/#?-B6pW-A">
                                                                                <field name="VAR" id="~!x~:D/4R3qKd*!yQ-mF" variabletype="">BB2_D</field>
                                                                                <value name="VALUE">
                                                                                  <block type="math_number" id="y]-.pEHr/f]+!zGBM5F#">
                                                                                    <field name="NUM">1.5</field>
                                                                                  </block>
                                                                                </value>
                                                                                <next>
                                                                                  <block type="variables_set" id="7i7_JSOQNAY{xo2~%|{;">
                                                                                    <field name="VAR" id="sD6f7dn-ob,Ie_1=[!$h" variabletype="">BB2_D_put</field>
                                                                                    <value name="VALUE">
                                                                                      <block type="math_number" id="4|?W_y:s![o$FNB?!Jdi">
                                                                                        <field name="NUM">1.5</field>
                                                                                      </block>
                                                                                    </value>
                                                                                    <next>
                                                                                      <block type="variables_set" id="~V~HW+ZsO}?]YEP$USOh">
                                                                                        <field name="VAR" id="/QW~Cvw)NmI.%iH~(nN|" variabletype="">M2_maior</field>
                                                                                        <value name="VALUE">
                                                                                          <block type="math_number" id="|{0b/,oBuK4Q@$9`oK2q">
                                                                                            <field name="NUM">40</field>
                                                                                          </block>
                                                                                        </value>
                                                                                        <next>
                                                                                          <block type="variables_set" id="B@MV%8F8^[h!D{$Rwz(2">
                                                                                            <field name="VAR" id="ULXVq9g#lv]PC_s4[SlW" variabletype="">M2_menor</field>
                                                                                            <value name="VALUE">
                                                                                              <block type="math_number" id="lm?qn$nZRbGXJi:`)eA1">
                                                                                                <field name="NUM">20</field>
                                                                                              </block>
                                                                                            </value>
                                                                                            <next>
                                                                                              <block type="variables_set" id="2x-_C|714N0gQd)|=Hn+">
                                                                                                <field name="VAR" id="R!$@JgrR*mH,uwwaS/^v" variabletype="">---------------------------BB_3--------------------</field>
                                                                                                <value name="VALUE">
                                                                                                  <block type="math_number" id="=^Xl^nwSi?[dE.YrDjc(">
                                                                                                    <field name="NUM">3</field>
                                                                                                  </block>
                                                                                                </value>
                                                                                                <next>
                                                                                                  <block type="variables_set" id="MqAJ^wXT3:jRWo9#),oH">
                                                                                                    <field name="VAR" id="%LA}kEq!/mN$Q^-B:=u:" variabletype="">BB3_P</field>
                                                                                                    <value name="VALUE">
                                                                                                      <block type="math_number" id="n=Y{yW?xY*vq(wPcIK*)">
                                                                                                        <field name="NUM">25</field>
                                                                                                      </block>
                                                                                                    </value>
                                                                                                    <next>
                                                                                                      <block type="variables_set" id="s,IkK,n,Yu+mjlk0]1ZH">
                                                                                                        <field name="VAR" id="PR..j]{X?C+NjosCDkR[" variabletype="">BB3_D</field>
                                                                                                        <value name="VALUE">
                                                                                                          <block type="math_number" id="EzXCW5-j}_UCfbm8dPmG">
                                                                                                            <field name="NUM">1.7</field>
                                                                                                          </block>
                                                                                                        </value>
                                                                                                        <next>
                                                                                                          <block type="variables_set" id="-!m596O5jCR*7iGwzx;8">
                                                                                                            <field name="VAR" id="TPj?iiokOb[PkJmjS+sJ" variabletype="">BB3_D_put</field>
                                                                                                            <value name="VALUE">
                                                                                                              <block type="math_number" id="z]kWP*2oUOxq):NZ0VA-">
                                                                                                                <field name="NUM">1.7</field>
                                                                                                              </block>
                                                                                                            </value>
                                                                                                            <next>
                                                                                                              <block type="variables_set" id="8M(Wc;iGn_d{TALYpH$!">
                                                                                                                <field name="VAR" id="ZkH?HE8K~|`%/Qbxs,#F" variabletype="">M3_maior</field>
                                                                                                                <value name="VALUE">
                                                                                                                  <block type="math_number" id="F]w@JXWOStj-h.Zz}]!B">
                                                                                                                    <field name="NUM">20</field>
                                                                                                                  </block>
                                                                                                                </value>
                                                                                                                <next>
                                                                                                                  <block type="variables_set" id="!`4~^D6TfAM1_d]mV6.d">
                                                                                                                    <field name="VAR" id="Tfu3z=_j,`nzBL|YI(?7" variabletype="">M3_menor</field>
                                                                                                                    <value name="VALUE">
                                                                                                                      <block type="math_number" id="b$_jg5A!*u10VLnEo`Ec">
                                                                                                                        <field name="NUM">5</field>
                                                                                                                      </block>
                                                                                                                    </value>
                                                                                                                    <next>
                                                                                                                      <block type="variables_set" id="qkLd.~VWx3o|%sz=g0L!">
                                                                                                                        <field name="VAR" id="_~Ty~5O{~)Xrt,.d!fG-" variabletype="">Segundos de cada nivel</field>
                                                                                                                        <value name="VALUE">
                                                                                                                          <block type="math_number" id="tZa;@2gTU$!TsuuyP_Tf">
                                                                                                                            <field name="NUM">2</field>
                                                                                                                          </block>
                                                                                                                        </value>
                                                                                                                        <next>
                                                                                                                          <block type="variables_set" id="oxl1lGqrj_R4YnW_tHD)" collapsed="true">
                                                                                                                            <field name="VAR" id="Kn4qHrV4+dSaa4n@]V-+" variabletype="">_sma_bb_kay</field>
                                                                                                                            <value name="VALUE">
                                                                                                                              <block type="text_prompt_ext" id="TMF.tVh!rZwJ}6#uJNI1" collapsed="true">
                                                                                                                                <mutation type="NUMBER"></mutation>
                                                                                                                                <field name="TYPE">NUMBER</field>
                                                                                                                                <value name="TEXT">
                                                                                                                                  <shadow type="text" id="]FN~8BMO;+R!VADx$sI[">
                                                                                                                                    <field name="TEXT">S E N H A </field>
                                                                                                                                  </shadow>
                                                                                                                                </value>
                                                                                                                              </block>
                                                                                                                            </value>
                                                                                                                          </block>
                                                                                                                        </next>
                                                                                                                      </block>
                                                                                                                    </next>
                                                                                                                  </block>
                                                                                                                </next>
                                                                                                              </block>
                                                                                                            </next>
                                                                                                          </block>
                                                                                                        </next>
                                                                                                      </block>
                                                                                                    </next>
                                                                                                  </block>
                                                                                                </next>
                                                                                              </block>
                                                                                            </next>
                                                                                          </block>
                                                                                        </next>
                                                                                      </block>
                                                                                    </next>
                                                                                  </block>
                                                                                </next>
                                                                              </block>
                                                                            </next>
                                                                          </block>
                                                                        </next>
                                                                      </block>
                                                                    </next>
                                                                  </block>
                                                                </next>
                                                              </block>
                                                            </next>
                                                          </block>
                                                        </next>
                                                      </block>
                                                    </next>
                                                  </block>
                                                </next>
                                              </block>
                                            </next>
                                          </block>
                                        </next>
                                      </block>
                                    </next>
                                  </block>
                                </next>
                              </block>
                            </next>
                          </block>
                        </next>
                      </block>
                    </next>
                  </block>
                </next>
              </block>
            </next>
          </block>
        </next>
      </block>
    </statement>
  </block>
</xml>